chuni_scanner/__init__.py
chuni_scanner/__main__.py
chuni_scanner/logger.py
chuni_scanner/scanner.py
chuni_scanner/schemas.py
chuni_scanner/sa/__init__.py
chuni_scanner/sa/engine.py
chuni_scanner/sa/tables.py
chuni_scanner-1.0.1.dist-info/licenses/LICENSE
chuni_scanner-1.0.1.dist-info/METADATA
chuni_scanner-1.0.1.dist-info/WHEEL
chuni_scanner-1.0.1.dist-info/entry_points.txt
chuni_scanner-1.0.1.dist-info/top_level.txt
chuni_scanner-1.0.1.dist-info/RECORD
