Metadata-Version: 2.4
Name: chuni-scanner
Version: 1.0.1
Summary: A simple chunithm music data scanner
Requires-Python: >=3.12
License-File: LICENSE
Requires-Dist: aiopath>=0.7.7
Requires-Dist: asyncmy>=0.2.10
Requires-Dist: coloredlogs>=15.0.1
Requires-Dist: greenlet>=3.2.3
Requires-Dist: pydantic>=2.11.7
Requires-Dist: ruff>=0.12.4
Requires-Dist: setuptools>=80.9.0
Requires-Dist: sqlalchemy>=2.0.41
Requires-Dist: twine>=6.1.0
Requires-Dist: wheel>=0.45.1
Dynamic: license-file
